giftless/__init__.py
giftless/app.py
giftless/config.py
giftless/error_handling.py
giftless/exc.py
giftless/representation.py
giftless/schema.py
giftless/util.py
giftless/view.py
giftless/wsgi_entrypoint.py
giftless/auth/__init__.py
giftless/auth/allow_anon.py
giftless/auth/github.py
giftless/auth/identity.py
giftless/auth/jwt.py
giftless/storage/__init__.py
giftless/storage/amazon_s3.py
giftless/storage/azure.py
giftless/storage/exc.py
giftless/storage/google_cloud.py
giftless/storage/local_storage.py
giftless/transfer/__init__.py
giftless/transfer/basic_external.py
giftless/transfer/basic_streaming.py
giftless/transfer/multipart.py
giftless/transfer/types.py
giftless-0.6.2.dist-info/LICENSE
giftless-0.6.2.dist-info/METADATA
giftless-0.6.2.dist-info/WHEEL
giftless-0.6.2.dist-info/top_level.txt
giftless-0.6.2.dist-info/RECORD
