Metadata-Version: 2.1
Name: giftless
Version: 0.6.2
Summary: A Git LFS Server implementation in Python with support for pluggable backends
Author: Vit Zikmund
Author-email: Shahar Evron <shahar.evron@datopian.com>, Rufus Pollock <hello@rufuspollock.com>, Adam Thornton <athornton@lsst.org>
License: Copyright 2020-2024 Datopian (Viderum, Inc.)
Project-URL: Homepage, https://giftless.datopian.com
Project-URL: Source, https://github.com/datopian/giftless
Project-URL: Issue tracker, https://github.com/datopian/giftless/issues
Keywords: git,git-lfs,datopian
Classifier: Development Status :: 5 - Production/Stable
Classifier: License :: OSI Approved :: MIT License
Classifier: Programming Language :: Python
Classifier: Programming Language :: Python :: 3
Classifier: Programming Language :: Python :: 3.10
Classifier: Programming Language :: Python :: 3.11
Classifier: Programming Language :: Python :: 3.12
Classifier: Natural Language :: English
Classifier: Operating System :: POSIX
Classifier: Typing :: Typed
Requires-Python: >=3.10
License-File: LICENSE
